{"41b4KI5aEjbBS4wwQ3bijQ==":"samaj-logo-96x91.png","nR1/GuxiB+oitd2rHNVtaw==":"img-1437x898.png","nfi7SbET6ZfZkOOZX8Q73w==":"raksha-302x379.png","qQRtF38RDIUEb91577DsLA==":"container-303x379.png","V5iT1Mp0MM1OK3k7MPStGA==":"container-1-303x379.png","EFLZ50wd7nvF5W3p3Cen6A==":"diwali-225x225.jpg","AiLzFPnUXlPo+eqLO+sW9w==":"kite-302x379.png","3HHVKc82xzoK9/Mb7C+MJQ==":"samaj-logo-615x580.png","5mA6eyAeo/E1wDGZ3q03JQ==":"wix-bg-image-472x486.png","vX4tuZ2WQRfB+i91kXJA0w==":"wix-bg-image-1-472x486.png","XqStexa3ucYeWEdbgE9USg==":"background1.jpg","1TOa8Fro0k99V2jSf/c5wA==":"1-612x408.jpg","knDyOjI/C1sq7A0GrPgxoQ==":"3-612x408.jpg","AQX307DjTi91K9VTgMiwzQ==":"5-612x408.jpg","EhKzTI/SC0twLDSUqkqnjg==":"dede-721x442.png","vtYva2Wp/s+dWBHJaC92nQ==":"unsplash_tyandmpxwhc-412x629.png","5//pdzpkkw2ZXfoDzhZ7ag==":"untitled%20design-451x652.png","Y5pbu6NNH7v+4uzCCr2ZGQ==":"namste-612x408.jpg","IAnk7Vi5soELKBGYSfITow==":"codifyformatter-408x612.jpg","3hpGZF1Ul1mph8mTfgjl2g==":"codifyformatter%20(1)-612x612.jpg","ug+gCryOYE3HkjVnvVS8Vw==":"2-1-612x408.jpg","ZGr2PONO/s9DiCkH4tnqUw==":"6-1-612x408.jpg"}